cloudbeat.py
cloudbeat_common/__init__.py
cloudbeat_common/json_util.py
cloudbeat_common/models.py
cloudbeat_common/reporter.py
cloudbeat_common_test1-0.0.3.dist-info/METADATA
cloudbeat_common_test1-0.0.3.dist-info/WHEEL
cloudbeat_common_test1-0.0.3.dist-info/top_level.txt
cloudbeat_common_test1-0.0.3.dist-info/RECORD
