Metadata-Version: 2.4
Name: cloudbeat-common-test1
Version: 0.0.3
Summary: Contains the common types and API client for CloudBeat
Home-page: https://cloudbeat.io/
Author: CBNR Cloud Solutions LTD
Author-email: info@cloudbeat.io
License: Apache-2.0
Project-URL: Source, https://github.com/cloudbeat-io/cb-kit-python
Keywords: cloudbeat testing reporting python
Classifier: Development Status :: 5 - Production/Stable
Classifier: Intended Audience :: Developers
Classifier: License :: OSI Approved :: Apache Software License
Classifier: Topic :: Software Development :: Quality Assurance
Classifier: Topic :: Software Development :: Testing
Classifier: Programming Language :: Python :: 3
Classifier: Programming Language :: Python :: 3 :: Only
Classifier: Programming Language :: Python :: 3.7
Classifier: Programming Language :: Python :: 3.8
Classifier: Programming Language :: Python :: 3.9
Classifier: Programming Language :: Python :: 3.10
Classifier: Programming Language :: Python :: 3.11
Classifier: Programming Language :: Python :: 3.12
Requires-Python: >=3.6
Requires-Dist: attrs>=16.0.0
Requires-Dist: pluggy>=0.4.0
Dynamic: author
Dynamic: author-email
Dynamic: classifier
Dynamic: description
Dynamic: description-content-type
Dynamic: home-page
Dynamic: keywords
Dynamic: license
Dynamic: project-url
Dynamic: requires-dist
Dynamic: requires-python
Dynamic: summary
